{"11013":{"id":11013,"name":"重力经纬","type":1,"value":"[31013]","img":"rune13","des":"佩戴之后，每1秒对最近的敌人造成[150%攻击力]伤害\n--没有人可以摆脱重力约束","cdTime":1,"defendCost":100,"value2":"[61014]","des2":"机械化效果:释放技能时会对5个单位造成[150%攻击力]的伤害"},"11056":{"id":11056,"name":"埃里克闹钟","type":1,"value":"[31062]","img":"rune54","des":"携带之后，每10秒，会增加30K攻速和300能量恢复，持续2秒\n--再睡一会，往后播播?","cdTime":10,"defendCost":100,"value2":"[61077]","des2":"机械化效果:额外提升20点能量恢复和500点攻速"},"81001":{"id":81001,"name":"龙珠","type":1,"value":"[81001]","img":"rune1001","des":"佩戴之后,每次普通攻击增加20点攻击力\n--说出你的愿望,任何愿望我都可以帮你实现","cdTime":0,"defendCost":100,"value2":"[91001]","des2":"机械化效果:每次普通攻击，额外增加180点攻击力"},"81002":{"id":81002,"name":"纸片人","type":1,"value":"[81003,81005]","img":"rune1002","des":"佩戴之后,每次普通攻击增加1点攻速，但携带后会降低亿点点攻速，持续300秒\n--价值昂贵的纸片人","cdTime":0,"defendCost":100,"value2":"[91003]","des2":"机械化效果:增加自身3000点攻速"},"81003":{"id":81003,"name":"零卡薯条","type":1,"value":"[81006]","img":"rune1003","des":"佩戴之后,每次普通攻击会恢复40点能量，但会降低2点能量恢复，持续5秒\n--没标，零卡！","cdTime":0,"defendCost":100,"value2":"[91006]","des2":"机械化效果:每次普通攻击，额外增加3点能量恢复，持续5秒"},"81004":{"id":81004,"name":"练功宝宝","type":1,"value":"[81009]","img":"rune1004","des":"佩戴之后,每次普通攻击会增加自身1点经验\n--你就不能找个能让我挂练兵房的地图嘛","cdTime":0,"defendCost":100,"value2":"[91009]","des2":"机械化效果:每次释放技能会增加自身1点经验"},"81005":{"id":81005,"name":"坚若磐石","type":1,"value":"[81011]","img":"rune1005","des":"佩戴之后,每次普通攻击会增加0.02%的普攻伤害\n--再也不喝有色饮料啦","cdTime":0,"defendCost":100,"value2":"[91011]","des2":"机械化效果:增加150%普攻伤害"},"81006":{"id":81006,"name":"学习计划","type":1,"value":"[81013]","img":"rune1006","des":"佩戴之后,直接伤害的系数增加[100%攻击力]\n--计划已经安排好了，玩会手机待会儿开整","cdTime":0,"defendCost":100,"value2":"[91013,91014]","des2":"机械化效果:增加50%普攻伤害和技能伤害"},"81007":{"id":81007,"name":"饲料","type":1,"value":"[81015]","img":"rune1007","des":"佩戴之后,每进行5次普通攻击，会额外触发一次主动技能\n--桐叶饲猪，肥大三倍，且易养","cdTime":0,"defendCost":100,"value2":"[91015]","des2":"机械化效果:每3秒额外释放一次主动技能"},"81008":{"id":81008,"name":"祖安问候","type":1,"value":"[81017]","img":"rune1008","des":"佩戴之后,每4秒为所有友军增加[友军的能量恢复*5]攻击力\n--死亡如风 常伴吾生","cdTime":4,"defendCost":100,"value2":"[91017]","des2":"机械化效果:每次普通攻击会增加所有友军3点能量恢复，持续6秒"},"81009":{"id":81009,"name":"紧急充值","type":1,"value":"[81019,81020,81021,81022]","img":"rune1009","des":"佩戴之后,当有敌人进入130码内，会暂时提升3000点攻速和60点能量恢复\n--你这儿弹窗，恰到好处","cdTime":0,"defendCost":100,"value2":"[91019,91020,91021,91022]","des2":"机械化效果：当有敌人进入130码内，额外提升3000点攻速和60点能量恢复"},"81010":{"id":81010,"name":"机械运输","type":1,"value":"[81023]","img":"rune1010","des":"佩戴之后,每当敌人在起始位置出现，对敌人造成[100%攻击力]伤害并增加自身1点能量恢复，持续20秒\n--早买早享受，晚买享折后","cdTime":0,"defendCost":100,"value2":"[91023]","des2":"机械化效果：增加自身30点能量恢复"},"81011":{"id":81011,"name":"加距飞行器","type":1,"value":"[81025]","img":"rune1011","des":"佩戴之后,普通攻击的距离提升为99999\n--明年过年买个无人机，绑个冲天大礼花试试","cdTime":0,"defendCost":100,"value2":"[91025]","des2":"机械化效果：普通攻击造成伤害时，每相隔100码，造成额外20%伤害"},"81012":{"id":81012,"name":"很蓝的啦","type":1,"value":"[81026,81027]","img":"rune1012","des":"佩戴之后,当130码内没有敌人时，增加自身100%的暴击几率和500%的暴击伤害\n--你要是真不行，把钱给我，我来，站桩我也会","cdTime":0,"defendCost":100,"value2":"[91026,91027]","des2":"机械化效果：当130码内没有敌人时，增加自身300%的暴击几率和1500%的暴击伤害"},"81013":{"id":81013,"name":"人生果","type":1,"value":"[81028]","img":"rune1013","des":"佩戴之后,技能伤害[包含符文]造成伤害时，每相隔100码，造成额外18%伤害\n--三千年一开花，三千年一结果，再三千年才得熟","cdTime":0,"defendCost":100,"value2":"[91028]","des2":"机械化效果：技能伤害[包含符文]造成伤害时，每相隔100码，增加造成额外18%伤害"},"81014":{"id":81014,"name":"巨龙之蛋","type":1,"value":"[81029]","img":"rune1014","des":"佩戴之后,每次释放技能，会增加[2*神器数量]的攻击力\n--Daenerys Targaryen","cdTime":0,"defendCost":100,"value2":"[91029,91029,91029,91029,91029,91029,91029,91029,91029,91029]","des2":"机械化效果：直接获得10个金蛋"},"81015":{"id":81015,"name":"号令之旗","type":1,"value":"[81031]","img":"rune1015","des":"佩戴之后,每次释放技能，会为所有友军增加0.4点攻速\n--全体起立","cdTime":0,"defendCost":100,"value2":"[91031]","des2":"机械化效果：增加自身30点能量恢复"},"81016":{"id":81016,"name":"述说之书","type":1,"value":"[81033]","img":"rune1016","des":"佩戴之后,降低35点能量上限\n--又吃鸡咯","cdTime":0,"defendCost":100,"value2":"[91033]","des2":"机械化效果：释放技能后，会回复自身45点能量"},"81017":{"id":81017,"name":"阵法","type":1,"value":"[81035]","img":"rune1017","des":"佩戴之后,每次释放技能，会为所有友军增加3点能量恢复，持续6秒\n--秘术！恢复大阵法！","cdTime":0,"defendCost":100,"value2":"[91035]","des2":"机械化效果：增加自身20点能量恢复"},"81018":{"id":81018,"name":"投降螃","type":1,"value":"[81037]","img":"rune1018","des":"佩戴之后,每次释放技能，会为1号位的友军增加0.05%的暴击几率\n--山本，你和你的仙人，投降不投降","cdTime":0,"defendCost":100,"value2":"[91037]","des2":"机械化效果：增加自身20点能量恢复"},"81019":{"id":81019,"name":"狂暴符文","type":1,"value":"[81039]","img":"rune1019","des":"佩戴之后,每次释放技能，增加自身0.1%的暴击伤害\n--生气鱼始终暴躁的原因找到了","cdTime":0,"defendCost":100,"value2":"[91039]","des2":"机械化效果：增加自身300%的暴击伤害"},"81020":{"id":81020,"name":"一盘鸡","type":1,"value":"[81041]","img":"rune1020","des":"佩戴之后,每800秒增加一层攻速增益，每层攻速增益提升10%的攻击速度\n--海参不够了，鸡吃不吃","cdTime":800,"defendCost":100,"value2":"[91041]","des2":"机械化效果：增加自身2000点攻速"},"81021":{"id":81021,"name":"鸟毛","type":1,"value":"[81043]","img":"rune1021","des":"佩戴之后,每40秒增加1点能量恢复\n--真的是鸡毛","cdTime":40,"defendCost":100,"value2":"[91043]","des2":"机械化效果：降低35点能量上限"},"81022":{"id":81022,"name":"牛仔裤","type":1,"value":"[81044]","img":"rune1022","des":"佩戴之后,增加350%的技能伤害\n--我要破洞牛仔裤，麻烦给我换一下","cdTime":0,"defendCost":100,"value2":"[91044]","des2":"机械化效果：每5秒增加0.5%的技能伤害"},"81023":{"id":81023,"name":"兔兔","type":1,"value":"[81046,81047]","img":"rune1023","des":"佩戴之后,每6秒增加1%的暴击几率并每点暴击几率增加1点攻击力\n--兔兔被吃了，只剩下印子了","cdTime":6,"defendCost":100,"value2":"[91046,91047]","des2":"机械化效果：增加300%的暴击几率和500K的攻击力"},"81024":{"id":81024,"name":"虎虎生威","type":1,"value":"[81048]","img":"rune1024","des":"佩戴之后,每点暴击率会提升1.5点暴击伤害\n--虎年，少打游戏，多陪家人，多赚money","cdTime":0,"defendCost":100,"value2":"[91048]","des2":"机械化效果：每次普通攻击增加0.08%的暴击几率"},"81025":{"id":81025,"name":"龟年鹤寿","type":1,"value":"[81050,81051]","img":"rune1025","des":"佩戴之后,每点暴击率会提升1点暴击伤害,并且技能可以触发暴击\n--立个flag，能活一万年","cdTime":0,"defendCost":100,"value2":"[91050,91051]","des2":"机械化效果：增加100%的暴击几率和200%的暴击伤害"},"81026":{"id":81026,"name":"阳光收集器","type":1,"value":"[81052]","img":"rune1026","des":"佩戴之后,每击杀100个敌人，可以增加1点能量恢复\n--僵尸怎么还不来？","cdTime":0,"defendCost":100,"value2":"[91052]","des2":"机械化效果：增加60%的普攻伤害和技能伤害"},"81027":{"id":81027,"name":"草莓","type":1,"value":"[81054]","img":"rune1027","des":"佩戴之后,每次对敌人造成伤害，增加目标[1.5%承受伤害],最多叠加30层\n--酸酸酸酸","cdTime":0,"defendCost":100,"value2":"[91054]","des2":"机械化效果：增加60%的普攻伤害和技能伤害"},"81028":{"id":81028,"name":"死亡之翼","type":1,"value":"[81056]","img":"rune1028","des":"佩戴之后,每秒对一个敌人放出死亡之翼，死亡之翼会对目标造成[100*攻击力]伤害\n--冲！","cdTime":1,"defendCost":100,"value2":"[91056]","des2":"机械化效果：增加150%的技能伤害"},"81029":{"id":81029,"name":"危险药剂","type":1,"value":"[81057]","img":"rune1029","des":"佩戴之后,每秒增加[等级*0.7]的攻击力\n--超级英雄也有心酸","cdTime":1,"defendCost":100,"value2":"[91057]","des2":"机械化效果：每秒额外增加[等级*0.7]的攻击力"},"81030":{"id":81030,"name":"冰棍","type":1,"value":"[81058]","img":"rune1030","des":"佩戴之后,每次升级增加[3%]的暴击伤害\n--别问，问就是绿豆沙","cdTime":0,"defendCost":100,"value2":"[91058]","des2":"机械化效果：降低25点升级所需的经验值"},"115001":{"id":115001,"name":"达布溜","type":2,"value":"[40001]","img":"rune101","des":"该神器非常逗比地给所有人加888攻击力~\n--你把握不住，交给我","cdTime":0,"defendCost":100,"value2":"[]","des2":"无机械化效果"},"115003":{"id":115003,"name":"神的笔记","type":2,"value":"[40003]","img":"rune103","des":"所有英雄增加10%暴击几率\n--记上谁的名字，谁就会心脏永远健康","cdTime":0,"defendCost":100,"value2":"[]","des2":"无机械化效果"},"115004":{"id":115004,"name":"超级眼镜","type":2,"value":"[40004]","img":"rune104","des":"所有英雄增加60点攻击速度\n--带上眼镜，看清楚，攻速变快，很合理","cdTime":0,"defendCost":100,"value2":"[]","des2":"无机械化效果"},"115005":{"id":115005,"name":"快乐水","type":2,"value":"[40005]","img":"rune105","des":"所有英雄增加3点能量恢复速度\n--点个外卖，送一瓶，开心","cdTime":0,"defendCost":100,"value2":"[]","des2":"无机械化效果"},"115007":{"id":115007,"name":"青涩的情书","type":2,"value":"[40007]","img":"rune106","des":"所有英雄增加20%暴击伤害\n--爱要勇敢表达哦","cdTime":0,"defendCost":100,"value2":"[]","des2":"无机械化效果"},"115008":{"id":115008,"name":"疯狂面具","type":2,"value":"[40038,40039]","img":"rune107","des":"所有英雄增加12%的普通攻击伤害和12%的技能伤害[包含符文]\n--你说我很疯狂，那你看看法外狂徒张三","cdTime":0,"defendCost":100,"value2":"[]","des2":"无机械化效果"},"115010":{"id":115010,"name":"烫手手里剑","type":2,"value":"[40014,40021]","img":"rune109","des":"所有英雄增加150点攻击速度，降低350点攻击力\n--这个手里剑很棒，除了有点烫","cdTime":0,"defendCost":100,"value2":"[]","des2":"无机械化效果"},"115011":{"id":115011,"name":"腐蚀手里剑","type":2,"value":"[40014,40025]","img":"rune110","des":"所有英雄增加150点攻击速度，降低2点能量恢复速度\n--这个手里剑更棒，有点费手而已","cdTime":0,"defendCost":100,"value2":"[]","des2":"无机械化效果"},"115012":{"id":115012,"name":"整蛊百宝箱","type":2,"value":"[40013,40024]","img":"rune111","des":"所有英雄增加15%暴击几率，降低40点攻击速度\n--我是整蛊之王","cdTime":0,"defendCost":100,"value2":"[]","des2":"无机械化效果"},"115013":{"id":115013,"name":"高科技手枪","type":2,"value":"[40013,40025]","img":"rune112","des":"所有英雄增加15%暴击几率，降低2点能量恢复速度\n--这个枪指哪不打哪儿","cdTime":0,"defendCost":100,"value2":"[]","des2":"无机械化效果"},"115014":{"id":115014,"name":"魔法帽帽","type":2,"value":"[40015,40021]","img":"rune113","des":"所有英雄增加5点能量恢复速度，降低350点攻击力\n--不提供魔法的魔法帽","cdTime":0,"defendCost":100,"value2":"[]","des2":"无机械化效果"},"115015":{"id":115015,"name":"大红帽","type":2,"value":"[40015,40024]","img":"rune114","des":"所有英雄增加5点能量恢复速度，降低40点攻击速度\n--灰太郎给小红帽准备的大帽子","cdTime":0,"defendCost":100,"value2":"[]","des2":"无机械化效果"},"115016":{"id":115016,"name":"吉他","type":2,"value":"[40008]","img":"rune115","des":"所有英雄增加15%的普通攻击伤害\n--谁娶了多愁善感的你 ，谁看了你的日记","cdTime":0,"defendCost":100,"value2":"[]","des2":"无机械化效果"},"115017":{"id":115017,"name":"锅","type":2,"value":"[40018,40021]","img":"rune116","des":"所有英雄增加20%的普通攻击伤害，降低350点攻击力\n--这个锅，它算是平底的嘛","cdTime":0,"defendCost":100,"value2":"[]","des2":"无机械化效果"},"115018":{"id":115018,"name":"缠绕蛋","type":2,"value":"[40018,40025]","img":"rune117","des":"所有英雄增加20%的普通攻击伤害，降低2点能量恢复速度\n--至于为什么叫缠绕蛋，我也不知道","cdTime":0,"defendCost":100,"value2":"[]","des2":"无机械化效果"},"115019":{"id":115019,"name":"VIP","type":2,"value":"[40017,40025]","img":"rune118","des":"所有英雄增加30%的暴击伤害，降低2点能量恢复速度\n--充值让我变得超强","cdTime":0,"defendCost":100,"value2":"[]","des2":"无机械化效果"},"115020":{"id":115020,"name":"钞票","type":2,"value":"[40017,40024]","img":"rune119","des":"所有英雄增加30%的暴击伤害，降低40点攻击速度\n--祝各位大把赚钱！","cdTime":0,"defendCost":100,"value2":"[]","des2":"无机械化效果"},"115021":{"id":115021,"name":"三连","type":2,"value":"[40019,40021]","img":"rune120","des":"所有英雄增加20%的技能伤害[包含符文]，降低350点攻击力\n--一键三连，点赞不花钱","cdTime":0,"defendCost":100,"value2":"[]","des2":"无机械化效果"},"115022":{"id":115022,"name":"魔法羽毛笔","type":2,"value":"[40019,40024]","img":"rune121","des":"所有英雄增加20%的技能伤害[包含符文]，降低40点攻击速度\n--这哪有键盘打字来得快","cdTime":0,"defendCost":100,"value2":"[]","des2":"无机械化效果"},"115023":{"id":115023,"name":"魔法符咒","type":2,"value":"[40009]","img":"rune122","des":"所有英雄增加15%的技能伤害[包含符文]\n--我需要更多的魔法\n--QEWWQR，拿来吧你","cdTime":0,"defendCost":100,"value2":"[]","des2":"无机械化效果"}}